ImgToolsGG/Clean_Images.py
ImgToolsGG/__init__.py
ImgToolsGG/expand_image.py
ImgToolsGG/get_exif_info.py
ImgToolsGG-0.3.45.dist-info/METADATA
ImgToolsGG-0.3.45.dist-info/WHEEL
ImgToolsGG-0.3.45.dist-info/top_level.txt
ImgToolsGG-0.3.45.dist-info/RECORD
